.gitignore
.pre-commit-config.yaml
CHANGELOG.md
Makefile
README.md
pytest.ini
requirements.txt
setup.py
test-requirements.txt
tox.ini
.circleci/config.yml
docs/.gitignore
docs/Makefile
docs/source/cli_tools.rst
docs/source/conf.py
docs/source/epic_kitchens.rst
docs/source/index.rst
docs/source/submission_format.md
docs/source/_static/epic-kitchens-logo.svg
docs/source/_static/favicon.ico
docs/source/_static/logo.png
docs/source/_static/theme_overrides.css
docs/source/meta/noun_classes.rst
docs/source/meta/test_timestamps.rst
docs/source/meta/train_action_labels.rst
docs/source/meta/train_action_narrations.rst
docs/source/meta/train_object_labels.rst
docs/source/meta/verb_classes.rst
docs/source/meta/video_descriptions.rst
docs/source/meta/video_info.rst
epic_kitchens/__init__.py
epic_kitchens/__version__.py
epic_kitchens/competition.py
epic_kitchens/labels.py
epic_kitchens/meta.py
epic_kitchens/metrics.py
epic_kitchens/scoring.py
epic_kitchens/time.py
epic_kitchens/video.py
epic_kitchens.egg-info/PKG-INFO
epic_kitchens.egg-info/SOURCES.txt
epic_kitchens.egg-info/dependency_links.txt
epic_kitchens.egg-info/entry_points.txt
epic_kitchens.egg-info/requires.txt
epic_kitchens.egg-info/top_level.txt
epic_kitchens/dataset/__init__.py
epic_kitchens/dataset/epic_dataset.py
epic_kitchens/dataset/video_dataset.py
epic_kitchens/gulp/__init__.py
epic_kitchens/gulp/__main__.py
epic_kitchens/gulp/adapter.py
epic_kitchens/gulp/visualisation.py
epic_kitchens/internal/__init__.py
epic_kitchens/internal/loading.py
epic_kitchens/internal/utils.py
epic_kitchens/preprocessing/__init__.py
epic_kitchens/preprocessing/split_segments.py
tests/__init__.py
tests/system_test_dataset.etag
tests/system/__init__.py
tests/system/gulp/__init__.py
tests/system/gulp/test_adapter.py
tests/system/meta/__init__.py
tests/system/meta/conftest.py
tests/system/meta/test_classes.py
tests/system/meta/test_descriptions.py
tests/system/meta/test_narrations.py
tests/system/meta/test_test.py
tests/system/meta/test_train.py
tests/system/meta/test_video_info.py
tests/system/preprocessing/__init__.py
tests/system/preprocessing/test_split_segments.py
tests/unit/__init__.py
tests/unit/test_metrics.py
tests/unit/test_scoring.py
